Workbook

Sheet Transactions
A1: Transaction ID | B1: Transaction Date | C1: Customer Name | D1: Region | E1: City | F1: Account Manager | G1: Product | H1: Product Type | I1: Quantity | J1: Unit Price (INR) | K1: Discount % | L1: Tax Included | M1: Currency | N1: Billing Cycle | O1: Payment Method | P1: Status | Q1: Renewal Date | R1: Net Amount | S1: Tax Amount (18% GST) | T1: Final Amount | U1: Quarter
A2: TXN-1000 | B2: 45753 | C2: SwiftLogic Labs | D2: North | E2: Jaipur | F2: SNEHA IYER | G2: Enterprise Plan | H2: Subscription | I2: 1 | J2: 9999 | K2: 0 | L2: Yes | M2: INR | N2: Monthly | O2: Cheque | P2: Active | Q2: 45783 | R2: =IF(P2="Active", I2*J2*(1-K2/100), 0) -> 9999 | S2: =IF(L2="Yes", R2-(R2/1.18), R2*0.18) -> 1525.2712 | T2: =IF(L2="Yes", R2, R2+S2) -> 9999 | U2: ="Q"&ROUNDUP(MONTH(IFERROR(DATEVALUE(B2), DATE(RIGHT(B2,4), MID(B2,4,2), LEFT(B2,2))))/3,0) -> Q2
A3: TXN-1001 | B3: 45553 | C3: MapleTech Solutions | D3: East | E3: Kolkata | F3: Sneha Iyer | G3: Training Session | H3: One-time | I3: 1 | J3: 4999 | K3: 15 | L3: Yes | M3: INR | N3: Quarterly | O3: Credit Card | P3: Active | R3: =IF(P3="Active", I3*J3*(1-K3/100), 0) -> 4249.15 | S3: =IF(L3="Yes", R3-(R3/1.18), R3*0.18) -> 648.17542 | T3: =IF(L3="Yes", R3, R3+S3) -> 4249.15 | U3: ="Q"&ROUNDUP(MONTH(IFERROR(DATEVALUE(B3), DATE(RIGHT(B3,4), MID(B3,4,2), LEFT(B3,2))))/3,0) -> Q3
A4: TXN-1002 | B4: 45572 | C4: RedOak Enterprises | D4: North | E4: Jaipur | F4: Rohan Kapoor | G4: Training Session | H4: One-time | I4: 1 | J4: 4999 | K4: 10 | L4: No | M4: INR | N4: Monthly | O4: UPI | P4: Paused | R4: =IF(P4="Active", I4*J4*(1-K4/100), 0) -> 0 | S4: =IF(L4="Yes", R4-(R4/1.18), R4*0.18) -> 0 | T4: =IF(L4="Yes", R4, R4+S4) -> 0 | U4: ="Q"&ROUNDUP(MONTH(IFERROR(DATEVALUE(B4), DATE(RIGHT(B4,4), MID(B4,4,2), LEFT(B4,2))))/3,0) -> Q4
A5: TXN-1003 | B5: 45510 | C5: Pinnacle Infra | D5: East | E5: Patna | F5: Arjun Das | G5: Enterprise Plan | H5: Subscription | I5: 1 | J5: 9999 | K5: 5 | L5: No | M5: INR | N5: Quarterly | O5: UPI | P5: Active | Q5: 45540 | R5: =IF(P5="Active", I5*J5*(1-K5/100), 0) -> 9499.05 | S5: =IF(L5="Yes", R5-(R5/1.18), R5*0.18) -> 1709.829 | T5: =IF(L5="Yes", R5, R5+S5) -> 11208.879 | U5: ="Q"&ROUNDUP(MONTH(IFERROR(DATEVALUE(B5), DATE(RIGHT(B5,4), MID(B5,4,2), LEFT(B5,2))))/3,0) -> Q3
A6: TXN-1004 | B6: 45764 | C6: VeloCity Networks | D6: North | E6: Jaipur | F6: ARJUN DAS | G6: API Add-on | H6: Add-on | I6: 1 | J6: 1499 | K6: 20 | L6: Yes | M6: INR | N6: Annual | O6: UPI | P6: Active | R6: =IF(P6="Active", I6*J6*(1-K6/100), 0) -> 1199.2 | S6: =IF(L6="Yes", R6-(R6/1.18), R6*0.18) -> 182.92881 | T6: =IF(L6="Yes", R6, R6+S6) -> 1199.2 | U6: ="Q"&ROUNDUP(MONTH(IFERROR(DATEVALUE(B6), DATE(RIGHT(B6,4), MID(B6,4,2), LEFT(B6,2))))/3,0) -> Q2
A7: TXN-1005 | B7: 45498 | C7: ThunderBolt Inc | D7: West | E7: Ahmedabad | F7: Sneha Iyer | G7: Enterprise Plan | H7: Subscription | I7: 1 | J7: 9999 | K7: 0 | L7: No | M7: INR | N7: Quarterly | O7: Cheque | P7: Refunded | R7: =IF(P7="Active", I7*J7*(1-K7/100), 0) -> 0 | S7: =IF(L7="Yes", R7-(R7/1.18), R7*0.18) -> 0 | T7: =IF(L7="Yes", R7, R7+S7) -> 0 | U7: ="Q"&ROUNDUP(MONTH(IFERROR(DATEVALUE(B7), DATE(RIGHT(B7,4), MID(B7,4,2), LEFT(B7,2))))/3,0) -> Q3
A8: TXN-1006 | B8: 45610 | C8: NorthStar Digital | D8: East | E8: Kolkata | F8: Vikram Mehta | G8: Onboarding Fee | H8: One-time | I8: 1 | J8: 14999 | K8: 15 | L8: Yes | M8: INR | N8: Monthly | O8: Bank Transfer | P8: Active | R8: =IF(P8="Active", I8*J8*(1-K8/100), 0) -> 12749.15 | S8: =IF(L8="Yes", R8-(R8/1.18), R8*0.18) -> 1944.7856 | T8: =IF(L8="Yes", R8, R8+S8) -> 12749.15 | U8: ="Q"&ROUNDUP(MONTH(IFERROR(DATEVALUE(B8), DATE(RIGHT(B8,4), MID(B8,4,2), LEFT(B8,2))))/3,0) -> Q4
A9: TXN-1007 | B9: 45556 | C9: EverGreen IT | D9: North | E9: Jaipur | F9: Rohan Kapoor | G9: Training Session | H9: One-time | I9: 3 | J9: 4999 | K9: 0.15 | L9: Yes | M9: INR | N9: MONTHLY | O9: UPI | P9: Active | R9: =IF(P9="Active", I9*J9*(1-K9/100), 0) -> 14974.504 | S9: =IF(L9="Yes", R9-(R9/1.18), R9*0.18) -> 2284.2464 | T9: =IF(L9="Yes", R9, R9+S9) -> 14974.504 | U9: ="Q"&ROUNDUP(MONTH(IFERROR(DATEVALUE(B9), DATE(RIGHT(B9,4), MID(B9,4,2), LEFT(B9,2))))/3,0) -> Q3
A10: TXN-1008 | B10: 45509 | C10: QuantumBit Labs | D10: North | E10: Chandigarh | F10: VIKRAM MEHTA | G10: Storage Upgrade | H10: Add-on | I10: 3 | J10: 799 | K10: 0 | L10: No | M10: INR | N10: annual | O10: Cheque | P10: Cancelled | R10: =IF(P10="Active", I10*J10*(1-K10/100), 0) -> 0 | S10: =IF(L10="Yes", R10-(R10/1.18), R10*0.18) -> 0 | T10: =IF(L10="Yes", R10, R10+S10) -> 0 | U10: ="Q"&ROUNDUP(MONTH(IFERROR(DATEVALUE(B10), DATE(RIGHT(B10,4), MID(B10,4,2), LEFT(B10,2))))/3,0) -> Q3
A11: TXN-1009 | B11: 45535 | C11: AlphaTrack Systems | D11: South | E11: Hyderabad | F11: Arjun Das | G11: API Add-on | H11: Add-on | I11: 1 | J11: 1499 | K11: 0.15 | L11: Yes | M11: INR | N11: Annual | O11: Credit Card | P11: Active | R11: =IF(P11="Active", I11*J11*(1-K11/100), 0) -> 1496.7515 | S11: =IF(L11="Yes", R11-(R11/1.18), R11*0.18) -> 228.31803 | T11: =IF(L11="Yes", R11, R11+S11) -> 1496.7515 | U11: ="Q"&ROUNDUP(MONTH(IFERROR(DATEVALUE(B11), DATE(RIGHT(B11,4), MID(B11,4,2), LEFT(B11,2))))/3,0) -> Q3
A12: TXN-1010 | B12: 45816 | C12: VeloCity Networks | D12: North | E12: Delhi | F12: ARJUN DAS | G12: Training Session | H12: One-time | I12: 3 | J12: 4999 | K12: 0.15 | L12: No | M12: INR | N12: Monthly | O12: Credit Card | P12: Active | R12: =IF(P12="Active", I12*J12*(1-K12/100), 0) -> 14974.504 | S12: =IF(L12="Yes", R12-(R12/1.18), R12*0.18) -> 2695.4108 | T12: =IF(L12="Yes", R12, R12+S12) -> 17669.915 | U12: ="Q"&ROUNDUP(MONTH(IFERROR(DATEVALUE(B12), DATE(RIGHT(B12,4), MID(B12,4,2), LEFT(B12,2))))/3,0) -> Q2
A13: TXN-1011 | B13: 45808 | C13: ThunderBolt Inc | D13: East | E13: Guwahati | F13: Pooja Nair | G13: API Add-on | H13: Add-on | I13: 1 | J13: 1499 | K13: 10 | L13: Yes | M13: INR | N13: Monthly | O13: Bank Transfer | P13: Churned | R13: =IF(P13="Active", I13*J13*(1-K13/100), 0) -> 0 | S13: =IF(L13="Yes", R13-(R13/1.18), R13*0.18) -> 0 | T13: =IF(L13="Yes", R13, R13+S13) -> 0 | U13: ="Q"&ROUNDUP(MONTH(IFERROR(DATEVALUE(B13), DATE(RIGHT(B13,4), MID(B13,4,2), LEFT(B13,2))))/3,0) -> Q2
A14: TXN-1012 | B14: 45755 | C14: ThunderBolt Inc | D14: South | E14: Hyderabad | F14: Sneha Iyer | G14: API Add-on | H14: Add-on | I14: 5 | J14: 1499 | K14: 0 | L14: No | M14: INR | N14: monthly | O14: Cheque | P14: Paused | R14: =IF(P14="Active", I14*J14*(1-K14/100), 0) -> 0 | S14: =IF(L14="Yes", R14-(R14/1.18), R14*0.18) -> 0 | T14: =IF(L14="Yes", R14, R14+S14) -> 0 | U14: ="Q"&ROUNDUP(MONTH(IFERROR(DATEVALUE(B14), DATE(RIGHT(B14,4), MID(B14,4,2), LEFT(B14,2))))/3,0) -> Q2
A15: TXN-1013 | B15: 45706 | C15: CloudNine Systems | D15: South | E15: Kochi | F15: Pooja Nair | G15: Pro Plan | H15: Subscription | I15: 1 | J15: 2999 | K15: 0.1 | L15: Yes | M15: INR | N15: quarterly | O15: Credit Card | P15: Cancelled | R15: =IF(P15="Active", I15*J15*(1-K15/100), 0) -> 0 | S15: =IF(L15="Yes", R15-(R15/1.18), R15*0.18) -> 0 | T15: =IF(L15="Yes", R15, R15+S15) -> 0 | U15: ="Q"&ROUNDUP(MONTH(IFERROR(DATEVALUE(B15), DATE(RIGHT(B15,4), MID(B15,4,2), LEFT(B15,2))))/3,0) -> Q1
A16: TXN-1014 | B16: 45745 | C16: SunRise Technologies | D16: North | E16: Jaipur | F16: Vikram Mehta | G16: Pro Plan | H16: Subscription | I16: 1 | J16: 2999 | K16: 0 | L16: Yes | M16: INR | N16: Monthly | O16: Bank Transfer | P16: Churned | R16: =IF(P16="Active", I16*J16*(1-K16/100), 0) -> 0 | S16: =IF(L16="Yes", R16-(R16/1.18), R16*0.18) -> 0 | T16: =IF(L16="Yes", R16, R16+S16) -> 0 | U16: ="Q"&ROUNDUP(MONTH(IFERROR(DATEVALUE(B16), DATE(RIGHT(B16,4), MID(B16,4,2), LEFT(B16,2))))/3,0) -> Q1
A17: TXN-1015 | B17: 45607 | C17: UrbanGrid Analytics | D17: North | E17: Lucknow | F17: Rohan Kapoor | G17: Onboarding Fee | H17: One-time | I17: 5 | J17: 14999 | K17: 10 | L17: No | M17: INR | N17: Annual | O17: Credit Card | P17: Active | R17: =IF(P17="Active", I17*J17*(1-K17/100), 0) -> 67495.5 | S17: =IF(L17="Yes", R17-(R17/1.18), R17*0.18) -> 12149.19 | T17: =IF(L17="Yes", R17, R17+S17) -> 79644.69 | U17: ="Q"&ROUNDUP(MONTH(IFERROR(DATEVALUE(B17), DATE(RIGHT(B17,4), MID(B17,4,2), LEFT(B17,2))))/3,0) -> Q4
A18: TXN-1016 | B18: 45652 | C18: TechSpark Solutions | D18: West | E18: Mumbai | F18: rohan kapoor | G18: Pro Plan | H18: Subscription | I18: 1 | J18: 2999 | K18: 10 | L18: Yes | M18: INR | N18: Quarterly | O18: Credit Card | P18: Active | Q18: 46017 | R18: =IF(P18="Active", I18*J18*(1-K18/100), 0) -> 2699.1 | S18: =IF(L18="Yes", R18-(R18/1.18), R18*0.18) -> 411.72712 | T18: =IF(L18="Yes", R18, R18+S18) -> 2699.1 | U18: ="Q"&ROUNDUP(MONTH(IFERROR(DATEVALUE(B18), DATE(RIGHT(B18,4), MID(B18,4,2), LEFT(B18,2))))/3,0) -> Q4
A19: TXN-1017 | B19: 45553 | C19: IronClad Security | D19: North | E19: Chandigarh | F19: Vikram Mehta | G19: Starter Plan | H19: Subscription | I19: 1 | J19: 999 | K19: 10 | L19: No | M19: INR | N19: Annual | O19: Credit Card | P19: Active | Q19: 45583 | R19: =IF(P19="Active", I19*J19*(1-K19/100), 0) -> 899.1 | S19: =IF(L19="Yes", R19-(R19/1.18), R19*0.18) -> 161.838 | T19: =IF(L19="Yes", R19, R19+S19) -> 1060.938 | U19: ="Q"&ROUNDUP(MONTH(IFERROR(DATEVALUE(B19), DATE(RIGHT(B19,4), MID(B19,4,2), LEFT(B19,2))))/3,0) -> Q3
A20: TXN-1018 | B20: 45608 | C20: ThunderBolt Inc | D20: East | E20: Kolkata | F20: Arjun Das | G20: Pro Plan | H20: Subscription | I20: 1 | J20: 2999 | K20: 15 | L20: Yes | M20: INR | N20: MONTHLY | O20: UPI | P20: Active | Q20: 45973 | R20: =IF(P20="Active", I20*J20*(1-K20/100), 0) -> 2549.15 | S20: =IF(L20="Yes", R20-(R20/1.18), R20*0.18) -> 388.85339 | T20: =IF(L20="Yes", R20, R20+S20) -> 2549.15 | U20: ="Q"&ROUNDUP(MONTH(IFERROR(DATEVALUE(B20), DATE(RIGHT(B20,4), MID(B20,4,2), LEFT(B20,2))))/3,0) -> Q4
A21: TXN-1019 | B21: 45494 | C21: BrightEdge Digital | D21: West | E21: Pune | F21: Arjun Das | G21: Pro Plan | H21: Subscription | I21: 1 | J21: 2999 | K21: 5 | L21: No | M21: INR | N21: Quarterly | O21: Bank Transfer | P21: Cancelled | R21: =IF(P21="Active", I21*J21*(1-K21/100), 0) -> 0 | S21: =IF(L21="Yes", R21-(R21/1.18), R21*0.18) -> 0 | T21: =IF(L21="Yes", R21, R21+S21) -> 0 | U21: ="Q"&ROUNDUP(MONTH(IFERROR(DATEVALUE(B21), DATE(RIGHT(B21,4), MID(B21,4,2), LEFT(B21,2))))/3,0) -> Q3
A22: TXN-1020 | B22: 45684 | C22: QuantumBit Labs | D22: South | E22: Chennai | F22: vikram mehta | G22: API Add-on | H22: Add-on | I22: 5 | J22: 1499 | K22: 10 | L22: Yes | M22: INR | N22: ANNUAL | O22: Bank Transfer | P22: Active | R22: =IF(P22="Active", I22*J22*(1-K22/100), 0) -> 6745.5 | S22: =IF(L22="Yes", R22-(R22/1.18), R22*0.18) -> 1028.9746 | T22: =IF(L22="Yes", R22, R22+S22) -> 6745.5 | U22: ="Q"&ROUNDUP(MONTH(IFERROR(DATEVALUE(B22), DATE(RIGHT(B22,4), MID(B22,4,2), LEFT(B22,2))))/3,0) -> Q1
A23: TXN-1021 | B23: 45678 | C23: MetroSync Corp | D23: West | E23: Ahmedabad | F23: sneha iyer | G23: Starter Plan | H23: Subscription | I23: 1 | J23: 999 | K23: 10 | L23: No | M23: INR | N23: Annual | O23: Credit Card | P23: Active | Q23: 45708 | R23: =IF(P23="Active", I23*J23*(1-K23/100), 0) -> 899.1 | S23: =IF(L23="Yes", R23-(R23/1.18), R23*0.18) -> 161.838 | T23: =IF(L23="Yes", R23, R23+S23) -> 1060.938 | U23: ="Q"&ROUNDUP(MONTH(IFERROR(DATEVALUE(B23), DATE(RIGHT(B23,4), MID(B23,4,2), LEFT(B23,2))))/3,0) -> Q1
A24: TXN-1022 | B24: 45634 | C24: TerraFirm Solutions | D24: South | E24: Hyderabad | F24: Vikram Mehta | G24: Pro Plan | H24: Subscription | I24: 1 | J24: 2999 | K24: 0 | L24: Yes | M24: INR | N24: annual | O24: Credit Card | P24: Active | Q24: 45999 | R24: =IF(P24="Active", I24*J24*(1-K24/100), 0) -> 2999 | S24: =IF(L24="Yes", R24-(R24/1.18), R24*0.18) -> 457.47458 | T24: =IF(L24="Yes", R24, R24+S24) -> 2999 | U24: ="Q"&ROUNDUP(MONTH(IFERROR(DATEVALUE(B24), DATE(RIGHT(B24,4), MID(B24,4,2), LEFT(B24,2))))/3,0) -> Q4
A25: TXN-1023 | B25: 45793 | C25: SunRise Technologies | D25: South | E25: Hyderabad | F25: Vikram Mehta | G25: API Add-on | H25: Add-on | I25: 1 | J25: 1499 | K25: 10 | L25: No | M25: INR | N25: Annual | O25: Bank Transfer | P25: Active | R25: =IF(P25="Active", I25*J25*(1-K25/100), 0) -> 1349.1 | S25: =IF(L25="Yes", R25-(R25/1.18), R25*0.18) -> 242.838 | T25: =IF(L25="Yes", R25, R25+S25) -> 1591.938 | U25: ="Q"&ROUNDUP(MONTH(IFERROR(DATEVALUE(B25), DATE(RIGHT(B25,4), MID(B25,4,2), LEFT(B25,2))))/3,0) -> Q2
A26: TXN-1024 | B26: 45754 | C26: MetroSync Corp | D26: West | E26: Surat | F26: Sneha Iyer | G26: Onboarding Fee | H26: One-time | I26: 1 | J26: 14999 | K26: 15 | L26: No | M26: INR | N26: Annual | O26: Bank Transfer | P26: Refunded | R26: =IF(P26="Active", I26*J26*(1-K26/100), 0) -> 0 | S26: =IF(L26="Yes", R26-(R26/1.18), R26*0.18) -> 0 | T26: =IF(L26="Yes", R26, R26+S26) -> 0 | U26: ="Q"&ROUNDUP(MONTH(IFERROR(DATEVALUE(B26), DATE(RIGHT(B26,4), MID(B26,4,2), LEFT(B26,2))))/3,0) -> Q2
A27: TXN-1025 | B27: 45791 | C27: EverGreen IT | D27: West | E27: Pune | F27: Vikram Mehta | G27: Onboarding Fee | H27: One-time | I27: 1 | J27: 14999 | K27: 5 | L27: Yes | M27: INR | N27: MONTHLY | O27: Credit Card | P27: Churned | R27: =IF(P27="Active", I27*J27*(1-K27/100), 0) -> 0 | S27: =IF(L27="Yes", R27-(R27/1.18), R27*0.18) -> 0 | T27: =IF(L27="Yes", R27, R27+S27) -> 0 | U27: ="Q"&ROUNDUP(MONTH(IFERROR(DATEVALUE(B27), DATE(RIGHT(B27,4), MID(B27,4,2), LEFT(B27,2))))/3,0) -> Q2
A28: TXN-1026 | B28: 45809 | C28: CoralReef Data | D28: West | E28: Pune | F28: Pooja Nair | G28: Onboarding Fee | H28: One-time | I28: 1 | J28: 14999 | K28: 5 | L28: Yes | M28: INR | N28: Annual | O28: Credit Card | P28: Active | R28: =IF(P28="Active", I28*J28*(1-K28/100), 0) -> 14249.05 | S28: =IF(L28="Yes", R28-(R28/1.18), R28*0.18) -> 2173.5839 | T28: =IF(L28="Yes", R28, R28+S28) -> 14249.05 | U28: ="Q"&ROUNDUP(MONTH(IFERROR(DATEVALUE(B28), DATE(RIGHT(B28,4), MID(B28,4,2), LEFT(B28,2))))/3,0) -> Q2
A29: TXN-1027 | B29: 45700 | C29: CoralReef Data | D29: South | E29: Kochi | F29: Rohan Kapoor | G29: Onboarding Fee | H29: One-time | I29: 5 | J29: 14999 | K29: 15 | L29: Yes | M29: INR | N29: Annual | O29: Cheque | P29: Churned | R29: =IF(P29="Active", I29*J29*(1-K29/100), 0) -> 0 | S29: =IF(L29="Yes", R29-(R29/1.18), R29*0.18) -> 0 | T29: =IF(L29="Yes", R29, R29+S29) -> 0 | U29: ="Q"&ROUNDUP(MONTH(IFERROR(DATEVALUE(B29), DATE(RIGHT(B29,4), MID(B29,4,2), LEFT(B29,2))))/3,0) -> Q1
A30: TXN-1028 | B30: 45794 | C30: MapleTech Solutions | D30: East | E30: Bhubaneswar | F30: Arjun Das | G30: Training Session | H30: One-time | I30: 2 | J30: 4999 | K30: 10 | L30: No | M30: INR | N30: Quarterly | O30: Bank Transfer | P30: Active | R30: =IF(P30="Active", I30*J30*(1-K30/100), 0) -> 8998.2 | S30: =IF(L30="Yes", R30-(R30/1.18), R30*0.18) -> 1619.676 | T30: =IF(L30="Yes", R30, R30+S30) -> 10617.876 | U30: ="Q"&ROUNDUP(MONTH(IFERROR(DATEVALUE(B30), DATE(RIGHT(B30,4), MID(B30,4,2), LEFT(B30,2))))/3,0) -> Q2
A31: TXN-1029 | B31: 45751 | C31: VeloCity Networks | D31: West | E31: Pune | F31: SNEHA IYER | G31: Onboarding Fee | H31: One-time | I31: 1 | J31: 14999 | K31: 15 | L31: Yes | M31: INR | N31: Annual | O31: Cheque | P31: Active | R31: =IF(P31="Active", I31*J31*(1-K31/100), 0) -> 12749.15 | S31: =IF(L31="Yes", R31-(R31/1.18), R31*0.18) -> 1944.7856 | T31: =IF(L31="Yes", R31, R31+S31) -> 12749.15 | U31: ="Q"&ROUNDUP(MONTH(IFERROR(DATEVALUE(B31), DATE(RIGHT(B31,4), MID(B31,4,2), LEFT(B31,2))))/3,0) -> Q2
A32: TXN-1030 | B32: 45688 | C32: TEST_ACCOUNT | D32: North | E32: Jaipur | F32: Pooja Nair | G32: Starter Plan | H32: Subscription | I32: 1 | J32: 999 | K32: 0.15 | L32: No | M32: INR | N32: Quarterly | O32: Cheque | P32: Churned | R32: =IF(P32="Active", I32*J32*(1-K32/100), 0) -> 0 | S32: =IF(L32="Yes", R32-(R32/1.18), R32*0.18) -> 0 | T32: =IF(L32="Yes", R32, R32+S32) -> 0 | U32: ="Q"&ROUNDUP(MONTH(IFERROR(DATEVALUE(B32), DATE(RIGHT(B32,4), MID(B32,4,2), LEFT(B32,2))))/3,0) -> Q1
A33: TXN-1031 | B33: 31-03-2025 | C33: ZenithBridge Consulting | D33: West | E33: Pune | F33: Pooja Nair | G33: Training Session | H33: One-time | I33: 2 | J33: 4999 | K33: 0 | L33: No | M33: INR | N33: quarterly | O33: UPI | P33: Active | R33: =IF(P33="Active", I33*J33*(1-K33/100), 0) -> 9998 | S33: =IF(L33="Yes", R33-(R33/1.18), R33*0.18) -> 1799.64 | T33: =IF(L33="Yes", R33, R33+S33) -> 11797.64 | U33: ="Q"&ROUNDUP(MONTH(IFERROR(DATEVALUE(B33), DATE(RIGHT(B33,4), MID(B33,4,2), LEFT(B33,2))))/3,0) -> Q1
A34: TXN-1032 | B34: 45616 | C34: RedOak Enterprises | D34: East | E34: Bhubaneswar | F34: Arjun Das | G34: API Add-on | H34: Add-on | I34: 2 | J34: 1499 | K34: 0 | L34: Yes | M34: INR | N34: Annual | O34: Credit Card | P34: Active | R34: =IF(P34="Active", I34*J34*(1-K34/100), 0) -> 2998 | S34: =IF(L34="Yes", R34-(R34/1.18), R34*0.18) -> 457.32203 | T34: =IF(L34="Yes", R34, R34+S34) -> 2998 | U34: ="Q"&ROUNDUP(MONTH(IFERROR(DATEVALUE(B34), DATE(RIGHT(B34,4), MID(B34,4,2), LEFT(B34,2))))/3,0) -> Q4
A35: TXN-1033 | B35: 45716 | C35: UrbanGrid Analytics | D35: North | E35: Chandigarh | F35: Vikram Mehta | G35: Enterprise Plan | H35: Subscription | I35: 1 | J35: 9999 | K35: 5 | L35: Yes | M35: INR | N35: Quarterly | O35: Credit Card | P35: Active | Q35: 45746 | R35: =IF(P35="Active", I35*J35*(1-K35/100), 0) -> 9499.05 | S35: =IF(L35="Yes", R35-(R35/1.18), R35*0.18) -> 1449.0076 | T35: =IF(L35="Yes", R35, R35+S35) -> 9499.05 | U35: ="Q"&ROUNDUP(MONTH(IFERROR(DATEVALUE(B35), DATE(RIGHT(B35,4), MID(B35,4,2), LEFT(B35,2))))/3,0) -> Q1
A36: TXN-1034 | B36: 45677 | C36: IronClad Security | D36: North | E36: Delhi | F36: Rohan Kapoor | G36: Starter Plan | H36: Subscription | I36: 1 | J36: 999 | K36: 0.15 | L36: Yes | M36: INR | N36: Annual | O36: Credit Card | P36: Cancelled | R36: =IF(P36="Active", I36*J36*(1-K36/100), 0) -> 0 | S36: =IF(L36="Yes", R36-(R36/1.18), R36*0.18) -> 0 | T36: =IF(L36="Yes", R36, R36+S36) -> 0 | U36: ="Q"&ROUNDUP(MONTH(IFERROR(DATEVALUE(B36), DATE(RIGHT(B36,4), MID(B36,4,2), LEFT(B36,2))))/3,0) -> Q1
A37: TXN-1035 | B37: 45480 | C37: UrbanGrid Analytics | D37: East | E37: Guwahati | F37: ARJUN DAS | G37: Onboarding Fee | H37: One-time | I37: 2 | J37: 14999 | K37: 10 | L37: No | M37: INR | N37: Quarterly | O37: UPI | P37: Cancelled | R37: =IF(P37="Active", I37*J37*(1-K37/100), 0) -> 0 | S37: =IF(L37="Yes", R37-(R37/1.18), R37*0.18) -> 0 | T37: =IF(L37="Yes", R37, R37+S37) -> 0 | U37: ="Q"&ROUNDUP(MONTH(IFERROR(DATEVALUE(B37), DATE(RIGHT(B37,4), MID(B37,4,2), LEFT(B37,2))))/3,0) -> Q3
A38: TXN-1036 | B38: 45518 | C38: SunRise Technologies | D38: West | E38: Surat | F38: Rohan Kapoor | G38: API Add-on | H38: Add-on | I38: 2 | J38: 1499 | K38: 20 | L38: Yes | M38: INR | N38: Annual | O38: UPI | P38: Active | R38: =IF(P38="Active", I38*J38*(1-K38/100), 0) -> 2398.4 | S38: =IF(L38="Yes", R38-(R38/1.18), R38*0.18) -> 365.85763 | T38: =IF(L38="Yes", R38, R38+S38) -> 2398.4 | U38: ="Q"&ROUNDUP(MONTH(IFERROR(DATEVALUE(B38), DATE(RIGHT(B38,4), MID(B38,4,2), LEFT(B38,2))))/3,0) -> Q3
A39: TXN-1037 | B39: 45833 | C39: FusionWave Media | D39: West | E39: Pune | F39: Arjun Das | G39: Starter Plan | H39: Subscription | I39: 1 | J39: 999 | K39: 0.1 | L39: No | M39: INR | N39: Monthly | O39: Bank Transfer | P39: Paused | R39: =IF(P39="Active", I39*J39*(1-K39/100), 0) -> 0 | S39: =IF(L39="Yes", R39-(R39/1.18), R39*0.18) -> 0 | T39: =IF(L39="Yes", R39, R39+S39) -> 0 | U39: ="Q"&ROUNDUP(MONTH(IFERROR(DATEVALUE(B39), DATE(RIGHT(B39,4), MID(B39,4,2), LEFT(B39,2))))/3,0) -> Q2
A40: TXN-1038 | B40: 45828 | C40: TEST_ACCOUNT | D40: West | E40: Surat | F40: VIKRAM MEHTA | G40: Training Session | H40: One-time | I40: 5 | J40: 4999 | K40: 20 | L40: No | M40: INR | N40: Quarterly | O40: Cheque | P40: Active | R40: =IF(P40="Active", I40*J40*(1-K40/100), 0) -> 19996 | S40: =IF(L40="Yes", R40-(R40/1.18), R40*0.18) -> 3599.28 | T40: =IF(L40="Yes", R40, R40+S40) -> 23595.28 | U40: ="Q"&ROUNDUP(MONTH(IFERROR(DATEVALUE(B40), DATE(RIGHT(B40,4), MID(B40,4,2), LEFT(B40,2))))/3,0) -> Q2
A41: TXN-1039 | B41: 45748 | C41: OceanView Partners | D41: East | E41: Patna | F41: Vikram Mehta | G41: Enterprise Plan | H41: Subscription | I41: 1 | J41: 9999 | K41: 5 | L41: No | M41: INR | N41: Quarterly | O41: UPI | P41: Active | Q41: 45778 | R41: =IF(P41="Active", I41*J41*(1-K41/100), 0) -> 9499.05 | S41: =IF(L41="Yes", R41-(R41/1.18), R41*0.18) -> 1709.829 | T41: =IF(L41="Yes", R41, R41+S41) -> 11208.879 | U41: ="Q"&ROUNDUP(MONTH(IFERROR(DATEVALUE(B41), DATE(RIGHT(B41,4), MID(B41,4,2), LEFT(B41,2))))/3,0) -> Q2
A42: TXN-1040 | B42: 45538 | C42: MetroSync Corp | D42: East | E42: Bhubaneswar | F42: Sneha Iyer | G42: Starter Plan | H42: Subscription | I42: 1 | J42: 999 | K42: 0.1 | L42: No | M42: INR | N42: Monthly | O42: Credit Card | P42: Active | Q42: 45903 | R42: =IF(P42="Active", I42*J42*(1-K42/100), 0) -> 998.001 | S42: =IF(L42="Yes", R42-(R42/1.18), R42*0.18) -> 179.64018 | T42: =IF(L42="Yes", R42, R42+S42) -> 1177.6412 | U42: ="Q"&ROUNDUP(MONTH(IFERROR(DATEVALUE(B42), DATE(RIGHT(B42,4), MID(B42,4,2), LEFT(B42,2))))/3,0) -> Q3
A43: TXN-1041 | B43: 45718 | C43: SkyHigh Innovations | D43: West | E43: Surat | F43: arjun das | G43: API Add-on | H43: Add-on | I43: 1 | J43: 1499 | K43: 0 | L43: Yes | M43: INR | N43: ANNUAL | O43: UPI | P43: Active | R43: =IF(P43="Active", I43*J43*(1-K43/100), 0) -> 1499 | S43: =IF(L43="Yes", R43-(R43/1.18), R43*0.18) -> 228.66102 | T43: =IF(L43="Yes", R43, R43+S43) -> 1499 | U43: ="Q"&ROUNDUP(MONTH(IFERROR(DATEVALUE(B43), DATE(RIGHT(B43,4), MID(B43,4,2), LEFT(B43,2))))/3,0) -> Q1
A44: TXN-1042 | B44: 45589 | C44: NexGen Software | D44: South | E44: Bangalore | F44: Pooja Nair | G44: Storage Upgrade | H44: Add-on | I44: 2 | J44: 799 | K44: 20 | L44: Yes | M44: INR | N44: Annual | O44: Credit Card | P44: Active | R44: =IF(P44="Active", I44*J44*(1-K44/100), 0) -> 1278.4 | S44: =IF(L44="Yes", R44-(R44/1.18), R44*0.18) -> 195.01017 | T44: =IF(L44="Yes", R44, R44+S44) -> 1278.4 | U44: ="Q"&ROUNDUP(MONTH(IFERROR(DATEVALUE(B44), DATE(RIGHT(B44,4), MID(B44,4,2), LEFT(B44,2))))/3,0) -> Q4
A45: TXN-1043 | B45: 45512 | C45: BluePeak Technologies | D45: South | E45: Chennai | F45: vikram mehta | G45: Starter Plan | H45: Subscription | I45: 1 | J45: 999 | K45: 0.15 | L45: Yes | M45: INR | N45: Monthly | O45: Cheque | P45: Active | Q45: 45542 | R45: =IF(P45="Active", I45*J45*(1-K45/100), 0) -> 997.5015 | S45: =IF(L45="Yes", R45-(R45/1.18), R45*0.18) -> 152.16125 | T45: =IF(L45="Yes", R45, R45+S45) -> 997.5015 | U45: ="Q"&ROUNDUP(MONTH(IFERROR(DATEVALUE(B45), DATE(RIGHT(B45,4), MID(B45,4,2), LEFT(B45,2))))/3,0) -> Q3
A46: TXN-1044 | B46: 45610 | C46: VeloCity Networks | D46: East | E46: Bhubaneswar | F46: Vikram Mehta | G46: API Add-on | H46: Add-on | I46: 1 | J46: 1499 | K46: 10 | L46: No | M46: INR | N46: Annual | O46: UPI | P46: Active | R46: =IF(P46="Active", I46*J46*(1-K46/100), 0) -> 1349.1 | S46: =IF(L46="Yes", R46-(R46/1.18), R46*0.18) -> 242.838 | T46: =IF(L46="Yes", R46, R46+S46) -> 1591.938 | U46: ="Q"&ROUNDUP(MONTH(IFERROR(DATEVALUE(B46), DATE(RIGHT(B46,4), MID(B46,4,2), LEFT(B46,2))))/3,0) -> Q4
A47: TXN-1015 | B47: 45607 | C47: UrbanGrid Analytics | D47: North | E47: Noida | F47: Rohan Kapoor | G47: Onboarding Fee | H47: One-time | I47: 6 | J47: 14999 | K47: 10 | L47: No | M47: INR | N47: Annual | O47: Credit Card | P47: Active | R47: =IF(P47="Active", I47*J47*(1-K47/100), 0) -> 80994.6 | S47: =IF(L47="Yes", R47-(R47/1.18), R47*0.18) -> 14579.028 | T47: =IF(L47="Yes", R47, R47+S47) -> 95573.628 | U47: ="Q"&ROUNDUP(MONTH(IFERROR(DATEVALUE(B47), DATE(RIGHT(B47,4), MID(B47,4,2), LEFT(B47,2))))/3,0) -> Q4
A48: TXN-1045 | B48: 45639 | C48: SilverLine Systems | D48: East | E48: Guwahati | F48: Vikram Mehta | G48: API Add-on | H48: Add-on | I48: 1 | J48: 1499 | K48: 0.15 | L48: Yes | M48: INR | N48: Monthly | O48: Bank Transfer | P48: Active | R48: =IF(P48="Active", I48*J48*(1-K48/100), 0) -> 1496.7515 | S48: =IF(L48="Yes", R48-(R48/1.18), R48*0.18) -> 228.31803 | T48: =IF(L48="Yes", R48, R48+S48) -> 1496.7515 | U48: ="Q"&ROUNDUP(MONTH(IFERROR(DATEVALUE(B48), DATE(RIGHT(B48,4), MID(B48,4,2), LEFT(B48,2))))/3,0) -> Q4
A49: TXN-1046 | B49: 45520 | C49: TEST_ACCOUNT | D49: West | E49: Ahmedabad | F49: Rohan Kapoor | G49: Enterprise Plan | H49: Subscription | I49: 1 | J49: 9999 | K49: 10 | L49: No | M49: INR | N49: Monthly | O49: Cheque | P49: Cancelled | R49: =IF(P49="Active", I49*J49*(1-K49/100), 0) -> 0 | S49: =IF(L49="Yes", R49-(R49/1.18), R49*0.18) -> 0 | T49: =IF(L49="Yes", R49, R49+S49) -> 0 | U49: ="Q"&ROUNDUP(MONTH(IFERROR(DATEVALUE(B49), DATE(RIGHT(B49,4), MID(B49,4,2), LEFT(B49,2))))/3,0) -> Q3
A50: TXN-1047 | B50: 45680 | C50: UrbanGrid Analytics | D50: West | E50: Mumbai | F50: Arjun Das | G50: Starter Plan | H50: Subscription | I50: 1 | J50: 999 | K50: 0 | L50: Yes | M50: INR | N50: Annual | O50: UPI | P50: Cancelled | R50: =IF(P50="Active", I50*J50*(1-K50/100), 0) -> 0 | S50: =IF(L50="Yes", R50-(R50/1.18), R50*0.18) -> 0 | T50: =IF(L50="Yes", R50, R50+S50) -> 0 | U50: ="Q"&ROUNDUP(MONTH(IFERROR(DATEVALUE(B50), DATE(RIGHT(B50,4), MID(B50,4,2), LEFT(B50,2))))/3,0) -> Q1
A51: TXN-1048 | B51: 45698 | C51: SandStone Labs | D51: West | E51: Mumbai | F51: Arjun Das | G51: Enterprise Plan | H51: Subscription | I51: 1 | J51: 9999 | K51: 0 | L51: Yes | M51: INR | N51: Annual | O51: Credit Card | P51: Paused | R51: =IF(P51="Active", I51*J51*(1-K51/100), 0) -> 0 | S51: =IF(L51="Yes", R51-(R51/1.18), R51*0.18) -> 0 | T51: =IF(L51="Yes", R51, R51+S51) -> 0 | U51: ="Q"&ROUNDUP(MONTH(IFERROR(DATEVALUE(B51), DATE(RIGHT(B51,4), MID(B51,4,2), LEFT(B51,2))))/3,0) -> Q1
A52: TXN-1049 | B52: 45552 | C52: GoldenGate Software | D52: North | E52: Chandigarh | F52: Vikram Mehta | G52: Training Session | H52: One-time | I52: 5 | J52: 4999 | K52: 10 | L52: Yes | M52: INR | N52: Quarterly | O52: Bank Transfer | P52: Active | R52: =IF(P52="Active", I52*J52*(1-K52/100), 0) -> 22495.5 | S52: =IF(L52="Yes", R52-(R52/1.18), R52*0.18) -> 3431.5169 | T52: =IF(L52="Yes", R52, R52+S52) -> 22495.5 | U52: ="Q"&ROUNDUP(MONTH(IFERROR(DATEVALUE(B52), DATE(RIGHT(B52,4), MID(B52,4,2), LEFT(B52,2))))/3,0) -> Q3
A53: TXN-1050 | B53: 45686 | C53: RedOak Enterprises | D53: South | E53: Chennai | F53: Vikram Mehta | G53: Training Session | H53: One-time | I53: 3 | J53: 4999 | K53: 0 | L53: No | M53: INR | N53: Quarterly | O53: Cheque | P53: Active | R53: =IF(P53="Active", I53*J53*(1-K53/100), 0) -> 14997 | S53: =IF(L53="Yes", R53-(R53/1.18), R53*0.18) -> 2699.46 | T53: =IF(L53="Yes", R53, R53+S53) -> 17696.46 | U53: ="Q"&ROUNDUP(MONTH(IFERROR(DATEVALUE(B53), DATE(RIGHT(B53,4), MID(B53,4,2), LEFT(B53,2))))/3,0) -> Q1
A54: TXN-1051 | B54: 45707 | C54: BrightEdge Digital | D54: West | E54: Surat | F54: Arjun Das | G54: Starter Plan | H54: Subscription | I54: 1 | J54: 999 | K54: 5 | L54: No | M54: USD | N54: Monthly | O54: Cheque | P54: Active | Q54: 46072 | R54: =IF(P54="Active", I54*J54*(1-K54/100), 0) -> 949.05 | S54: =IF(L54="Yes", R54-(R54/1.18), R54*0.18) -> 170.829 | T54: =IF(L54="Yes", R54, R54+S54) -> 1119.879 | U54: ="Q"&ROUNDUP(MONTH(IFERROR(DATEVALUE(B54), DATE(RIGHT(B54,4), MID(B54,4,2), LEFT(B54,2))))/3,0) -> Q1
A55: TXN-1052 | B55: 45643 | C55: RedOak Enterprises | D55: West | E55: Pune | F55: VIKRAM MEHTA | G55: API Add-on | H55: Add-on | I55: 2 | J55: 1499 | K55: 20 | L55: Yes | M55: INR | N55: Monthly | O55: UPI | P55: Active | R55: =IF(P55="Active", I55*J55*(1-K55/100), 0) -> 2398.4 | S55: =IF(L55="Yes", R55-(R55/1.18), R55*0.18) -> 365.85763 | T55: =IF(L55="Yes", R55, R55+S55) -> 2398.4 | U55: ="Q"&ROUNDUP(MONTH(IFERROR(DATEVALUE(B55), DATE(RIGHT(B55,4), MID(B55,4,2), LEFT(B55,2))))/3,0) -> Q4
A56: TXN-1053 | B56: 45668 | C56: ZenithBridge Consulting | D56: West | E56: Mumbai | F56: Arjun Das | G56: Training Session | H56: One-time | I56: 5 | J56: 4999 | K56: 20 | L56: Yes | M56: INR | N56: Monthly | O56: UPI | P56: Churned | R56: =IF(P56="Active", I56*J56*(1-K56/100), 0) -> 0 | S56: =IF(L56="Yes", R56-(R56/1.18), R56*0.18) -> 0 | T56: =IF(L56="Yes", R56, R56+S56) -> 0 | U56: ="Q"&ROUNDUP(MONTH(IFERROR(DATEVALUE(B56), DATE(RIGHT(B56,4), MID(B56,4,2), LEFT(B56,2))))/3,0) -> Q1
A57: TXN-1054 | B57: 45488 | C57: VeloCity Networks | D57: North | E57: Lucknow | F57: Vikram Mehta | G57: Pro Plan | H57: Subscription | I57: 1 | J57: 2999 | K57: 10 | L57: No | M57: INR | N57: quarterly | O57: Bank Transfer | P57: Active | Q57: 45518 | R57: =IF(P57="Active", I57*J57*(1-K57/100), 0) -> 2699.1 | S57: =IF(L57="Yes", R57-(R57/1.18), R57*0.18) -> 485.838 | T57: =IF(L57="Yes", R57, R57+S57) -> 3184.938 | U57: ="Q"&ROUNDUP(MONTH(IFERROR(DATEVALUE(B57), DATE(RIGHT(B57,4), MID(B57,4,2), LEFT(B57,2))))/3,0) -> Q3
A58: TXN-1055 | B58: 45592 | C58: FusionWave Media | D58: North | E58: Lucknow | F58: Sneha Iyer | G58: Storage Upgrade | H58: Add-on | I58: 1 | J58: 799 | K58: 0 | L58: No | M58: INR | N58: Quarterly | O58: Cheque | P58: Churned | R58: =IF(P58="Active", I58*J58*(1-K58/100), 0) -> 0 | S58: =IF(L58="Yes", R58-(R58/1.18), R58*0.18) -> 0 | T58: =IF(L58="Yes", R58, R58+S58) -> 0 | U58: ="Q"&ROUNDUP(MONTH(IFERROR(DATEVALUE(B58), DATE(RIGHT(B58,4), MID(B58,4,2), LEFT(B58,2))))/3,0) -> Q4
A59: TXN-1056 | B59: 45670 | C59: CrystalPeak Analytics | D59: East | E59: Guwahati | F59: Arjun Das | G59: Onboarding Fee | H59: One-time | I59: 1 | J59: 14999 | K59: 0.15 | L59: Yes | M59: USD | N59: Quarterly | O59: Cheque | P59: Active | R59: =IF(P59="Active", I59*J59*(1-K59/100), 0) -> 14976.502 | S59: =IF(L59="Yes", R59-(R59/1.18), R59*0.18) -> 2284.5511 | T59: =IF(L59="Yes", R59, R59+S59) -> 14976.502 | U59: ="Q"&ROUNDUP(MONTH(IFERROR(DATEVALUE(B59), DATE(RIGHT(B59,4), MID(B59,4,2), LEFT(B59,2))))/3,0) -> Q1
A60: TXN-1057 | B60: 45591 | C60: OceanView Partners | D60: North | E60: Delhi | F60: Pooja Nair | G60: Storage Upgrade | H60: Add-on | I60: 1 | J60: 799 | K60: 5 | L60: Yes | M60: INR | N60: Annual | O60: Credit Card | P60: Cancelled | R60: =IF(P60="Active", I60*J60*(1-K60/100), 0) -> 0 | S60: =IF(L60="Yes", R60-(R60/1.18), R60*0.18) -> 0 | T60: =IF(L60="Yes", R60, R60+S60) -> 0 | U60: ="Q"&ROUNDUP(MONTH(IFERROR(DATEVALUE(B60), DATE(RIGHT(B60,4), MID(B60,4,2), LEFT(B60,2))))/3,0) -> Q4
A61: TXN-1058 | B61: 45625 | C61: IronClad Security | D61: West | E61: Mumbai | F61: Arjun Das | G61: Storage Upgrade | H61: Add-on | I61: 2 | J61: 799 | K61: 0 | L61: Yes | M61: INR | N61: Quarterly | O61: UPI | P61: Refunded | R61: =IF(P61="Active", I61*J61*(1-K61/100), 0) -> 0 | S61: =IF(L61="Yes", R61-(R61/1.18), R61*0.18) -> 0 | T61: =IF(L61="Yes", R61, R61+S61) -> 0 | U61: ="Q"&ROUNDUP(MONTH(IFERROR(DATEVALUE(B61), DATE(RIGHT(B61,4), MID(B61,4,2), LEFT(B61,2))))/3,0) -> Q4
A62: TXN-1059 | B62: 45589 | C62: TEST_ACCOUNT | D62: East | E62: Patna | F62: Vikram Mehta | G62: Training Session | H62: One-time | I62: 5 | J62: 4999 | K62: 15 | L62: No | M62: USD | N62: Annual | O62: Credit Card | P62: Paused | R62: =IF(P62="Active", I62*J62*(1-K62/100), 0) -> 0 | S62: =IF(L62="Yes", R62-(R62/1.18), R62*0.18) -> 0 | T62: =IF(L62="Yes", R62, R62+S62) -> 0 | U62: ="Q"&ROUNDUP(MONTH(IFERROR(DATEVALUE(B62), DATE(RIGHT(B62,4), MID(B62,4,2), LEFT(B62,2))))/3,0) -> Q4
A63: TXN-1060 | B63: 45529 | C63: CoralReef Data | D63: East | E63: Patna | F63: Pooja Nair | G63: Storage Upgrade | H63: Add-on | I63: -2 | J63: 799 | K63: 0.1 | L63: Yes | M63: INR | N63: Annual | O63: Cheque | P63: Cancelled | R63: =IF(P63="Active", I63*J63*(1-K63/100), 0) -> 0 | S63: =IF(L63="Yes", R63-(R63/1.18), R63*0.18) -> 0 | T63: =IF(L63="Yes", R63, R63+S63) -> 0 | U63: ="Q"&ROUNDUP(MONTH(IFERROR(DATEVALUE(B63), DATE(RIGHT(B63,4), MID(B63,4,2), LEFT(B63,2))))/3,0) -> Q3
A64: TXN-1061 | B64: 45726 | C64: IronClad Security | D64: West | E64: Mumbai | F64: Vikram Mehta | G64: Enterprise Plan | H64: Subscription | I64: 1 | J64: 9999 | K64: 0.1 | L64: No | M64: INR | N64: Quarterly | O64: Bank Transfer | P64: Active | Q64: 45816 | R64: =IF(P64="Active", I64*J64*(1-K64/100), 0) -> 9989.001 | S64: =IF(L64="Yes", R64-(R64/1.18), R64*0.18) -> 1798.0202 | T64: =IF(L64="Yes", R64, R64+S64) -> 11787.021 | U64: ="Q"&ROUNDUP(MONTH(IFERROR(DATEVALUE(B64), DATE(RIGHT(B64,4), MID(B64,4,2), LEFT(B64,2))))/3,0) -> Q1
A65: TXN-1062 | B65: 45701 | C65: BluePeak Technologies | D65: West | E65: Surat | F65: Vikram Mehta | G65: Starter Plan | H65: Subscription | I65: 1 | J65: 999 | K65: 0 | L65: Yes | M65: INR | N65: Quarterly | O65: UPI | P65: Paused | R65: =IF(P65="Active", I65*J65*(1-K65/100), 0) -> 0 | S65: =IF(L65="Yes", R65-(R65/1.18), R65*0.18) -> 0 | T65: =IF(L65="Yes", R65, R65+S65) -> 0 | U65: ="Q"&ROUNDUP(MONTH(IFERROR(DATEVALUE(B65), DATE(RIGHT(B65,4), MID(B65,4,2), LEFT(B65,2))))/3,0) -> Q1
A66: TXN-1063 | B66: 45484 | C66: MetroSync Corp | D66: North | E66: Lucknow | F66: Sneha Iyer | G66: Pro Plan | H66: Subscription | I66: 1 | J66: 2999 | K66: 0 | L66: No | M66: INR | N66: MONTHLY | O66: Bank Transfer | P66: Refunded | R66: =IF(P66="Active", I66*J66*(1-K66/100), 0) -> 0 | S66: =IF(L66="Yes", R66-(R66/1.18), R66*0.18) -> 0 | T66: =IF(L66="Yes", R66, R66+S66) -> 0 | U66: ="Q"&ROUNDUP(MONTH(IFERROR(DATEVALUE(B66), DATE(RIGHT(B66,4), MID(B66,4,2), LEFT(B66,2))))/3,0) -> Q3
A67: TXN-1064 | B67: 45548 | C67: VeloCity Networks | D67: East | E67: Bhubaneswar | F67: ROHAN KAPOOR | G67: Training Session | H67: One-time | I67: 3 | J67: 4999 | K67: 0 | L67: Yes | M67: INR | N67: monthly | O67: Bank Transfer | P67: Active | R67: =IF(P67="Active", I67*J67*(1-K67/100), 0) -> 14997 | S67: =IF(L67="Yes", R67-(R67/1.18), R67*0.18) -> 2287.678 | T67: =IF(L67="Yes", R67, R67+S67) -> 14997 | U67: ="Q"&ROUNDUP(MONTH(IFERROR(DATEVALUE(B67), DATE(RIGHT(B67,4), MID(B67,4,2), LEFT(B67,2))))/3,0) -> Q3
A68: TXN-1065 | B68: 45532 | C68: PixelCraft Studios | D68: North | E68: Chandigarh | F68: VIKRAM MEHTA | G68: Starter Plan | H68: Subscription | I68: 1 | J68: 999 | K68: 10 | L68: Yes | M68: INR | N68: Monthly | O68: Credit Card | P68: Active | Q68: 45897 | R68: =IF(P68="Active", I68*J68*(1-K68/100), 0) -> 899.1 | S68: =IF(L68="Yes", R68-(R68/1.18), R68*0.18) -> 137.15085 | T68: =IF(L68="Yes", R68, R68+S68) -> 899.1 | U68: ="Q"&ROUNDUP(MONTH(IFERROR(DATEVALUE(B68), DATE(RIGHT(B68,4), MID(B68,4,2), LEFT(B68,2))))/3,0) -> Q3
A69: TXN-1066 | B69: 45679 | C69: NorthStar Digital | D69: East | E69: Guwahati | F69: VIKRAM MEHTA | G69: Onboarding Fee | H69: One-time | I69: 1 | J69: 14999 | K69: 20 | L69: Yes | M69: INR | N69: Monthly | O69: UPI | P69: Active | R69: =IF(P69="Active", I69*J69*(1-K69/100), 0) -> 11999.2 | S69: =IF(L69="Yes", R69-(R69/1.18), R69*0.18) -> 1830.3864 | T69: =IF(L69="Yes", R69, R69+S69) -> 11999.2 | U69: ="Q"&ROUNDUP(MONTH(IFERROR(DATEVALUE(B69), DATE(RIGHT(B69,4), MID(B69,4,2), LEFT(B69,2))))/3,0) -> Q1
A70: TXN-1067 | B70: 45833 | C70: PixelCraft Studios | D70: West | E70: Ahmedabad | F70: Rohan Kapoor | G70: API Add-on | H70: Add-on | I70: 5 | J70: 1499 | K70: 0.1 | L70: Yes | M70: INR | N70: Monthly | O70: Cheque | P70: Refunded | R70: =IF(P70="Active", I70*J70*(1-K70/100), 0) -> 0 | S70: =IF(L70="Yes", R70-(R70/1.18), R70*0.18) -> 0 | T70: =IF(L70="Yes", R70, R70+S70) -> 0 | U70: ="Q"&ROUNDUP(MONTH(IFERROR(DATEVALUE(B70), DATE(RIGHT(B70,4), MID(B70,4,2), LEFT(B70,2))))/3,0) -> Q2
A71: TXN-1068 | B71: 45552 | C71: SilverLine Systems | D71: West | E71: Mumbai | F71: Pooja Nair | G71: Starter Plan | H71: Subscription | I71: 1 | J71: 999 | K71: 0 | L71: Yes | M71: INR | N71: Monthly | O71: Credit Card | P71: Churned | R71: =IF(P71="Active", I71*J71*(1-K71/100), 0) -> 0 | S71: =IF(L71="Yes", R71-(R71/1.18), R71*0.18) -> 0 | T71: =IF(L71="Yes", R71, R71+S71) -> 0 | U71: ="Q"&ROUNDUP(MONTH(IFERROR(DATEVALUE(B71), DATE(RIGHT(B71,4), MID(B71,4,2), LEFT(B71,2))))/3,0) -> Q3
A72: TXN-1069 | B72: 45621 | C72: ZenithBridge Consulting | D72: North | E72: Lucknow | F72: Pooja Nair | G72: Starter Plan | H72: Subscription | I72: 1 | J72: 999 | K72: 0.15 | L72: Yes | M72: INR | N72: Monthly | O72: UPI | P72: Active | Q72: 45986 | R72: =IF(P72="Active", I72*J72*(1-K72/100), 0) -> 997.5015 | S72: =IF(L72="Yes", R72-(R72/1.18), R72*0.18) -> 152.16125 | T72: =IF(L72="Yes", R72, R72+S72) -> 997.5015 | U72: ="Q"&ROUNDUP(MONTH(IFERROR(DATEVALUE(B72), DATE(RIGHT(B72,4), MID(B72,4,2), LEFT(B72,2))))/3,0) -> Q4
A73: TXN-1070 | B73: 45792 | C73: TidalWave Tech | D73: North | E73: Jaipur | F73: Sneha Iyer | G73: Storage Upgrade | H73: Add-on | I73: 5 | J73: 799 | K73: 0.15 | L73: Yes | M73: INR | N73: Annual | O73: UPI | P73: Paused | R73: =IF(P73="Active", I73*J73*(1-K73/100), 0) -> 0 | S73: =IF(L73="Yes", R73-(R73/1.18), R73*0.18) -> 0 | T73: =IF(L73="Yes", R73, R73+S73) -> 0 | U73: ="Q"&ROUNDUP(MONTH(IFERROR(DATEVALUE(B73), DATE(RIGHT(B73,4), MID(B73,4,2), LEFT(B73,2))))/3,0) -> Q2
A74: TXN-1071 | B74: 45546 | C74: ZenithBridge Consulting | D74: East | E74: Kolkata | F74: Sneha Iyer | G74: Enterprise Plan | H74: Subscription | I74: 1 | J74: 9999 | K74: 0 | L74: No | M74: INR | N74: Monthly | O74: UPI | P74: Refunded | R74: =IF(P74="Active", I74*J74*(1-K74/100), 0) -> 0 | S74: =IF(L74="Yes", R74-(R74/1.18), R74*0.18) -> 0 | T74: =IF(L74="Yes", R74, R74+S74) -> 0 | U74: ="Q"&ROUNDUP(MONTH(IFERROR(DATEVALUE(B74), DATE(RIGHT(B74,4), MID(B74,4,2), LEFT(B74,2))))/3,0) -> Q3
A75: TXN-1072 | B75: 45819 | C75: IronClad Security | D75: East | E75: Kolkata | F75: sneha iyer | G75: Pro Plan | H75: Subscription | I75: 1 | J75: 2999 | K75: 15 | L75: Yes | M75: INR | N75: Quarterly | O75: Credit Card | P75: Active | Q75: 45909 | R75: =IF(P75="Active", I75*J75*(1-K75/100), 0) -> 2549.15 | S75: =IF(L75="Yes", R75-(R75/1.18), R75*0.18) -> 388.85339 | T75: =IF(L75="Yes", R75, R75+S75) -> 2549.15 | U75: ="Q"&ROUNDUP(MONTH(IFERROR(DATEVALUE(B75), DATE(RIGHT(B75,4), MID(B75,4,2), LEFT(B75,2))))/3,0) -> Q2
A76: TXN-1073 | B76: 45497 | C76: ThunderBolt Inc | D76: North | E76: Jaipur | F76: Rohan Kapoor | G76: Onboarding Fee | H76: One-time | I76: 3 | J76: 14999 | K76: 5 | L76: Yes | M76: INR | N76: Monthly | O76: Credit Card | P76: Active | R76: =IF(P76="Active", I76*J76*(1-K76/100), 0) -> 42747.15 | S76: =IF(L76="Yes", R76-(R76/1.18), R76*0.18) -> 6520.7517 | T76: =IF(L76="Yes", R76, R76+S76) -> 42747.15 | U76: ="Q"&ROUNDUP(MONTH(IFERROR(DATEVALUE(B76), DATE(RIGHT(B76,4), MID(B76,4,2), LEFT(B76,2))))/3,0) -> Q3
A77: TXN-1074 | B77: 45730 | C77: TechSpark Solutions | D77: West | E77: Surat | F77: Sneha Iyer | G77: Enterprise Plan | H77: Subscription | I77: 1 | J77: 9999 | K77: 10 | L77: Yes | M77: INR | N77: ANNUAL | O77: Credit Card | P77: Active | Q77: 45820 | R77: =IF(P77="Active", I77*J77*(1-K77/100), 0) -> 8999.1 | S77: =IF(L77="Yes", R77-(R77/1.18), R77*0.18) -> 1372.7441 | T77: =IF(L77="Yes", R77, R77+S77) -> 8999.1 | U77: ="Q"&ROUNDUP(MONTH(IFERROR(DATEVALUE(B77), DATE(RIGHT(B77,4), MID(B77,4,2), LEFT(B77,2))))/3,0) -> Q1
A78: TXN-1075 | B78: 45561 | C78: ThunderBolt Inc | D78: West | E78: Surat | F78: Vikram Mehta | G78: Starter Plan | H78: Subscription | I78: 1 | J78: 999 | K78: 10 | L78: No | M78: INR | N78: Monthly | O78: Credit Card | P78: Active | Q78: 45651 | R78: =IF(P78="Active", I78*J78*(1-K78/100), 0) -> 899.1 | S78: =IF(L78="Yes", R78-(R78/1.18), R78*0.18) -> 161.838 | T78: =IF(L78="Yes", R78, R78+S78) -> 1060.938 | U78: ="Q"&ROUNDUP(MONTH(IFERROR(DATEVALUE(B78), DATE(RIGHT(B78,4), MID(B78,4,2), LEFT(B78,2))))/3,0) -> Q3
A79: TXN-1076 | B79: 45745 | C79: IronClad Security | D79: East | E79: Bhubaneswar | F79: SNEHA IYER | G79: Starter Plan | H79: Subscription | I79: 1 | J79: 999 | K79: 10 | L79: Yes | M79: INR | N79: Annual | O79: UPI | P79: Active | Q79: 45775 | R79: =IF(P79="Active", I79*J79*(1-K79/100), 0) -> 899.1 | S79: =IF(L79="Yes", R79-(R79/1.18), R79*0.18) -> 137.15085 | T79: =IF(L79="Yes", R79, R79+S79) -> 899.1 | U79: ="Q"&ROUNDUP(MONTH(IFERROR(DATEVALUE(B79), DATE(RIGHT(B79,4), MID(B79,4,2), LEFT(B79,2))))/3,0) -> Q1
A80: TXN-1077 | B80: 45770 | C80: FusionWave Media | D80: South | E80: Bangalore | F80: Pooja Nair | G80: Enterprise Plan | H80: Subscription | I80: 1 | J80: 9999 | K80: 0.15 | L80: Yes | M80: INR | N80: Annual | O80: Credit Card | P80: Cancelled | R80: =IF(P80="Active", I80*J80*(1-K80/100), 0) -> 0 | S80: =IF(L80="Yes", R80-(R80/1.18), R80*0.18) -> 0 | T80: =IF(L80="Yes", R80, R80+S80) -> 0 | U80: ="Q"&ROUNDUP(MONTH(IFERROR(DATEVALUE(B80), DATE(RIGHT(B80,4), MID(B80,4,2), LEFT(B80,2))))/3,0) -> Q2
A81: TXN-1078 | B81: 45511 | C81: TEST_ACCOUNT | D81: West | E81: Ahmedabad | F81: Arjun Das | G81: Training Session | H81: One-time | I81: -2 | J81: 4999 | K81: 10 | L81: Yes | M81: INR | N81: Monthly | O81: Cheque | P81: Churned | R81: =IF(P81="Active", I81*J81*(1-K81/100), 0) -> 0 | S81: =IF(L81="Yes", R81-(R81/1.18), R81*0.18) -> 0 | T81: =IF(L81="Yes", R81, R81+S81) -> 0 | U81: ="Q"&ROUNDUP(MONTH(IFERROR(DATEVALUE(B81), DATE(RIGHT(B81,4), MID(B81,4,2), LEFT(B81,2))))/3,0) -> Q3
A82: TXN-1079 | B82: 45717 | C82: CoralReef Data | D82: North | E82: Lucknow | F82: Rohan Kapoor | G82: Training Session | H82: One-time | I82: 1 | J82: 4999 | K82: 10 | L82: Yes | M82: USD | N82: Monthly | O82: Cheque | P82: Paused | R82: =IF(P82="Active", I82*J82*(1-K82/100), 0) -> 0 | S82: =IF(L82="Yes", R82-(R82/1.18), R82*0.18) -> 0 | T82: =IF(L82="Yes", R82, R82+S82) -> 0 | U82: ="Q"&ROUNDUP(MONTH(IFERROR(DATEVALUE(B82), DATE(RIGHT(B82,4), MID(B82,4,2), LEFT(B82,2))))/3,0) -> Q1
A83: TXN-1080 | B83: 45821 | C83: MapleTech Solutions | D83: South | E83: Hyderabad | F83: Arjun Das | G83: Starter Plan | H83: Subscription | I83: 1 | J83: 999 | K83: 10 | L83: No | M83: INR | N83: Monthly | O83: Bank Transfer | P83: Active | Q83: 45911 | R83: =IF(P83="Active", I83*J83*(1-K83/100), 0) -> 899.1 | S83: =IF(L83="Yes", R83-(R83/1.18), R83*0.18) -> 161.838 | T83: =IF(L83="Yes", R83, R83+S83) -> 1060.938 | U83: ="Q"&ROUNDUP(MONTH(IFERROR(DATEVALUE(B83), DATE(RIGHT(B83,4), MID(B83,4,2), LEFT(B83,2))))/3,0) -> Q2
A84: TXN-1081 | B84: 45517 | C84: NexGen Software | D84: South | E84: Hyderabad | F84: POOJA NAIR | G84: Starter Plan | H84: Subscription | I84: 1 | J84: 999 | K84: 10 | L84: No | M84: INR | N84: Annual | O84: Cheque | P84: Churned | R84: =IF(P84="Active", I84*J84*(1-K84/100), 0) -> 0 | S84: =IF(L84="Yes", R84-(R84/1.18), R84*0.18) -> 0 | T84: =IF(L84="Yes", R84, R84+S84) -> 0 | U84: ="Q"&ROUNDUP(MONTH(IFERROR(DATEVALUE(B84), DATE(RIGHT(B84,4), MID(B84,4,2), LEFT(B84,2))))/3,0) -> Q3
A85: TXN-1082 | B85: 45722 | C85: EverGreen IT | D85: East | E85: Kolkata | F85: arjun das | G85: Starter Plan | H85: Subscription | I85: 1 | J85: 999 | K85: 0 | L85: No | M85: INR | N85: Monthly | O85: Credit Card | P85: Active | Q85: 46087 | R85: =IF(P85="Active", I85*J85*(1-K85/100), 0) -> 999 | S85: =IF(L85="Yes", R85-(R85/1.18), R85*0.18) -> 179.82 | T85: =IF(L85="Yes", R85, R85+S85) -> 1178.82 | U85: ="Q"&ROUNDUP(MONTH(IFERROR(DATEVALUE(B85), DATE(RIGHT(B85,4), MID(B85,4,2), LEFT(B85,2))))/3,0) -> Q1
A86: TXN-1083 | B86: 45793 | C86: ZenithBridge Consulting | D86: South | E86: Kochi | F86: sneha iyer | G86: Enterprise Plan | H86: Subscription | I86: 1 | J86: 9999 | K86: 20 | L86: Yes | M86: INR | N86: Quarterly | O86: UPI | P86: Active | Q86: 46158 | R86: =IF(P86="Active", I86*J86*(1-K86/100), 0) -> 7999.2 | S86: =IF(L86="Yes", R86-(R86/1.18), R86*0.18) -> 1220.2169 | T86: =IF(L86="Yes", R86, R86+S86) -> 7999.2 | U86: ="Q"&ROUNDUP(MONTH(IFERROR(DATEVALUE(B86), DATE(RIGHT(B86,4), MID(B86,4,2), LEFT(B86,2))))/3,0) -> Q2
A87: TXN-1084 | B87: 45821 | C87: MapleTech Solutions | D87: South | E87: Chennai | F87: Pooja Nair | G87: Starter Plan | H87: Subscription | I87: 1 | J87: 999 | K87: 20 | L87: No | M87: INR | N87: Quarterly | O87: Bank Transfer | P87: Refunded | R87: =IF(P87="Active", I87*J87*(1-K87/100), 0) -> 0 | S87: =IF(L87="Yes", R87-(R87/1.18), R87*0.18) -> 0 | T87: =IF(L87="Yes", R87, R87+S87) -> 0 | U87: ="Q"&ROUNDUP(MONTH(IFERROR(DATEVALUE(B87), DATE(RIGHT(B87,4), MID(B87,4,2), LEFT(B87,2))))/3,0) -> Q2
A88: TXN-1085 | B88: 45526 | C88: CoreAxis Consulting | D88: East | E88: Kolkata | F88: Pooja Nair | G88: Onboarding Fee | H88: One-time | I88: 3 | J88: 14999 | K88: 10 | L88: No | M88: INR | N88: Monthly | O88: Cheque | P88: Active | R88: =IF(P88="Active", I88*J88*(1-K88/100), 0) -> 40497.3 | S88: =IF(L88="Yes", R88-(R88/1.18), R88*0.18) -> 7289.514 | T88: =IF(L88="Yes", R88, R88+S88) -> 47786.814 | U88: ="Q"&ROUNDUP(MONTH(IFERROR(DATEVALUE(B88), DATE(RIGHT(B88,4), MID(B88,4,2), LEFT(B88,2))))/3,0) -> Q3
A89: TXN-1086 | B89: 45665 | C89: NexGen Software | D89: South | E89: Kochi | F89: Vikram Mehta | G89: Starter Plan | H89: Subscription | I89: 1 | J89: 999 | K89: 10 | L89: Yes | M89: INR | N89: Quarterly | O89: Bank Transfer | P89: Active | Q89: 45695 | R89: =IF(P89="Active", I89*J89*(1-K89/100), 0) -> 899.1 | S89: =IF(L89="Yes", R89-(R89/1.18), R89*0.18) -> 137.15085 | T89: =IF(L89="Yes", R89, R89+S89) -> 899.1 | U89: ="Q"&ROUNDUP(MONTH(IFERROR(DATEVALUE(B89), DATE(RIGHT(B89,4), MID(B89,4,2), LEFT(B89,2))))/3,0) -> Q1
A90: TXN-1087 | B90: 10-08-2024 | C90: SkyHigh Innovations | D90: West | E90: Pune | G90: Training Session | H90: One-time | I90: 1 | J90: 4999 | K90: 0.1 | L90: Yes | M90: INR | N90: Annual | O90: Bank Transfer | P90: Paused | R90: =IF(P90="Active", I90*J90*(1-K90/100), 0) -> 0 | S90: =IF(L90="Yes", R90-(R90/1.18), R90*0.18) -> 0 | T90: =IF(L90="Yes", R90, R90+S90) -> 0 | U90: ="Q"&ROUNDUP(MONTH(IFERROR(DATEVALUE(B90), DATE(RIGHT(B90,4), MID(B90,4,2), LEFT(B90,2))))/3,0) -> Q4
A91: TXN-1088 | B91: 45506 | C91: IronClad Security | D91: North | E91: Delhi | F91: Pooja Nair | G91: Enterprise Plan | H91: Subscription | I91: 1 | J91: 9999 | K91: 0.15 | L91: Yes | M91: INR | N91: Annual | O91: UPI | P91: Active | Q91: 45596 | R91: =IF(P91="Active", I91*J91*(1-K91/100), 0) -> 9984.0015 | S91: =IF(L91="Yes", R91-(R91/1.18), R91*0.18) -> 1522.9833 | T91: =IF(L91="Yes", R91, R91+S91) -> 9984.0015 | U91: ="Q"&ROUNDUP(MONTH(IFERROR(DATEVALUE(B91), DATE(RIGHT(B91,4), MID(B91,4,2), LEFT(B91,2))))/3,0) -> Q3
A92: TXN-1089 | B92: 45742 | C92: TechSpark Solutions | D92: East | E92: Bhubaneswar | F92: pooja nair | G92: Storage Upgrade | H92: Add-on | I92: 1 | J92: 799 | K92: 0.1 | L92: No | M92: INR | N92: Annual | O92: Credit Card | P92: Active | R92: =IF(P92="Active", I92*J92*(1-K92/100), 0) -> 798.201 | S92: =IF(L92="Yes", R92-(R92/1.18), R92*0.18) -> 143.67618 | T92: =IF(L92="Yes", R92, R92+S92) -> 941.87718 | U92: ="Q"&ROUNDUP(MONTH(IFERROR(DATEVALUE(B92), DATE(RIGHT(B92,4), MID(B92,4,2), LEFT(B92,2))))/3,0) -> Q1
A93: TXN-1090 | B93: 45597 | C93: RedOak Enterprises | D93: East | E93: Patna | F93: Vikram Mehta | G93: Onboarding Fee | H93: One-time | I93: 5 | J93: 14999 | K93: 0.15 | L93: Yes | M93: INR | N93: quarterly | O93: Bank Transfer | P93: Refunded | R93: =IF(P93="Active", I93*J93*(1-K93/100), 0) -> 0 | S93: =IF(L93="Yes", R93-(R93/1.18), R93*0.18) -> 0 | T93: =IF(L93="Yes", R93, R93+S93) -> 0 | U93: ="Q"&ROUNDUP(MONTH(IFERROR(DATEVALUE(B93), DATE(RIGHT(B93,4), MID(B93,4,2), LEFT(B93,2))))/3,0) -> Q4
A94: TXN-1091 | B94: 20-02-2025 | C94: CoralReef Data | D94: West | E94: Pune | F94: SNEHA IYER | G94: Training Session | H94: One-time | I94: 1 | J94: 4999 | K94: 5 | L94: No | M94: INR | N94: Quarterly | O94: Cheque | P94: Churned | R94: =IF(P94="Active", I94*J94*(1-K94/100), 0) -> 0 | S94: =IF(L94="Yes", R94-(R94/1.18), R94*0.18) -> 0 | T94: =IF(L94="Yes", R94, R94+S94) -> 0 | U94: ="Q"&ROUNDUP(MONTH(IFERROR(DATEVALUE(B94), DATE(RIGHT(B94,4), MID(B94,4,2), LEFT(B94,2))))/3,0) -> Q1
A95: TXN-1092 | B95: 45809 | C95: TerraFirm Solutions | D95: North | E95: Chandigarh | F95: Arjun Das | G95: Starter Plan | H95: Subscription | I95: 1 | J95: 999 | K95: 10 | L95: No | M95: INR | N95: Quarterly | O95: Bank Transfer | P95: Active | Q95: 45899 | R95: =IF(P95="Active", I95*J95*(1-K95/100), 0) -> 899.1 | S95: =IF(L95="Yes", R95-(R95/1.18), R95*0.18) -> 161.838 | T95: =IF(L95="Yes", R95, R95+S95) -> 1060.938 | U95: ="Q"&ROUNDUP(MONTH(IFERROR(DATEVALUE(B95), DATE(RIGHT(B95,4), MID(B95,4,2), LEFT(B95,2))))/3,0) -> Q2
A96: TXN-1093 | B96: 45782 | C96: SandStone Labs | D96: East | E96: Patna | F96: Vikram Mehta | G96: Training Session | H96: One-time | I96: 1 | J96: 4999 | K96: 10 | L96: Yes | M96: INR | N96: Quarterly | O96: Cheque | P96: Active | R96: =IF(P96="Active", I96*J96*(1-K96/100), 0) -> 4499.1 | S96: =IF(L96="Yes", R96-(R96/1.18), R96*0.18) -> 686.30339 | T96: =IF(L96="Yes", R96, R96+S96) -> 4499.1 | U96: ="Q"&ROUNDUP(MONTH(IFERROR(DATEVALUE(B96), DATE(RIGHT(B96,4), MID(B96,4,2), LEFT(B96,2))))/3,0) -> Q2
A97: TXN-1094 | B97: 45788 | C97: Pinnacle Infra | D97: West | E97: Ahmedabad | F97: Vikram Mehta | G97: API Add-on | H97: Add-on | I97: 1 | J97: 1499 | K97: 0 | L97: No | M97: INR | N97: Annual | O97: Bank Transfer | P97: Active | R97: =IF(P97="Active", I97*J97*(1-K97/100), 0) -> 1499 | S97: =IF(L97="Yes", R97-(R97/1.18), R97*0.18) -> 269.82 | T97: =IF(L97="Yes", R97, R97+S97) -> 1768.82 | U97: ="Q"&ROUNDUP(MONTH(IFERROR(DATEVALUE(B97), DATE(RIGHT(B97,4), MID(B97,4,2), LEFT(B97,2))))/3,0) -> Q2
A98: TXN-1095 | B98: 45661 | C98: GreenLeaf Ventures | D98: South | E98: Kochi | F98: SNEHA IYER | G98: Pro Plan | H98: Subscription | I98: 1 | J98: 2999 | K98: 0 | L98: Yes | M98: INR | N98: Annual | O98: Credit Card | P98: Cancelled | R98: =IF(P98="Active", I98*J98*(1-K98/100), 0) -> 0 | S98: =IF(L98="Yes", R98-(R98/1.18), R98*0.18) -> 0 | T98: =IF(L98="Yes", R98, R98+S98) -> 0 | U98: ="Q"&ROUNDUP(MONTH(IFERROR(DATEVALUE(B98), DATE(RIGHT(B98,4), MID(B98,4,2), LEFT(B98,2))))/3,0) -> Q1
A99: TXN-1096 | B99: 45569 | C99: CoreAxis Consulting | D99: East | E99: Guwahati | F99: arjun das | G99: Starter Plan | H99: Subscription | I99: 1 | J99: 999 | K99: 0.1 | L99: Yes | M99: INR | N99: Quarterly | O99: UPI | P99: Active | Q99: 45934 | R99: =IF(P99="Active", I99*J99*(1-K99/100), 0) -> 998.001 | S99: =IF(L99="Yes", R99-(R99/1.18), R99*0.18) -> 152.23744 | T99: =IF(L99="Yes", R99, R99+S99) -> 998.001 | U99: ="Q"&ROUNDUP(MONTH(IFERROR(DATEVALUE(B99), DATE(RIGHT(B99,4), MID(B99,4,2), LEFT(B99,2))))/3,0) -> Q4
A100: TXN-1097 | B100: 45701 | C100: SandStone Labs | D100: South | E100: Bangalore | F100: Vikram Mehta | G100: Enterprise Plan | H100: Subscription | I100: 1 | J100: 9999 | K100: 10 | L100: No | M100: INR | N100: ANNUAL | O100: UPI | P100: Cancelled | R100: =IF(P100="Active", I100*J100*(1-K100/100), 0) -> 0 | S100: =IF(L100="Yes", R100-(R100/1.18), R100*0.18) -> 0 | T100: =IF(L100="Yes", R100, R100+S100) -> 0 | U100: ="Q"&ROUNDUP(MONTH(IFERROR(DATEVALUE(B100), DATE(RIGHT(B100,4), MID(B100,4,2), LEFT(B100,2))))/3,0) -> Q1
...

Sheet Questions
A1: Questions | B1: Answers
A2: List 3 issues (anomalies) you found in the dataset and explain how it affects the analysis | B2: 1. Date/Month Inconsistency: The dataset used mixed date formats (e.g., YYYY-MM-DD and DD-MM-YYYY), which caused standard date-extraction formulas to fail. I implemented a robust DATEVALUE and TRIM fallback formula to ensure accurate Quarter (Q1–Q4) and MoM mapping. 2. Tax Calculation Mismatches: Manual entries for "Tax Amount" and "Final Amount" were inconsistent with the 18% GST rule for "Tax Included" vs. "Excluded" rows. I standardized these using conditional logic to prevent revenue reporting errors. 3. String Normalization (Casing/Spaces): Inconsistent capitalization (e.g., "Arjun Das" vs "ARJUN DAS") and trailing spaces in the "Status" column threatened to skew unique customer counts. I utilized UPPER(TRIM()) logic to ensure data integrity for all pivot and lookup operations.
A3: Fill the following columns in the Transactions sheet using formulas. Leave the formula intact — do NOT paste as values. 1. "Net Amount" (Column R) = Quantity × Unit Price (INR) × (1 − Discount%) - Apply ONLY for rows where Status = "Active" - For all other statuses, Net Amount = 0 2. "Tax Amount (18% GST)" (Column S): - If Tax Included = "Yes": Tax Amount = Net Amount − (Net Amount / 1.18) - If Tax Included = "No": Tax Amount = Net Amount × 0.18 3. "Final Amount" (Column T): - If Tax Included = "Yes": Final Amount = Net Amount - If Tax Included = "No": Final Amount = Net Amount + Tax Amount 4. "Quarter" (Column U) = Extract the calendar quarter from Transaction Date (Q1, Q2, Q3, Q4) Write "Done" in cell B2 once formulas are in place. | B3: 1. =IF(P2="Active", I2*J2*(1-(K2/100)), 0) 2. =IF(L2="Yes", R2-(R2/1.18), R2*0.18) 3. =IF(L2="Yes", R2, R2+S2) 4. ="Q"&ROUNDUP(MONTH(IFERROR(DATEVALUE(B2), DATE(RIGHT(B2,4), MID(B2,4,2), LEFT(B2,2))))/3,0)
A4: Create a new subsheet named "Region Summary" with a pivot table showing: - Rows: Region - Values: Total Final Amount, Count of Active Transactions, Average Discount % (Include ONLY Active status & INR currency transactions) In cell B3, write which Region has the highest Average Final Amount per Active transaction. | B4: =IFERROR(__xludf.DUMMYFUNCTION("INDEX(SORT(FILTER({'Region Summary'!A2:A1000,'Region Summary'!B2:B1000/'Region Summary'!C2:C1000},'Region Summary'!A2:A1000<>""""),2,FALSE),1,1)"),"North") -> North
A5: What is the total Final Amount from "Subscription" type products where: - Status = "Active" - Currency = "INR" - Discount % is a valid percentage (i.e., between 0 and 100, not a decimal like 0.10 or 0.15) Write the formula-based answer in cell B4. | B5: =SUMPRODUCT((Transactions!H2:H2000="Subscription")*(Transactions!P2:P2000="Active")*(Transactions!M2:M2000="INR")*(Transactions!K2:K2000>=0)*(Transactions!K2:K2000<=100)*(Transactions!T2:T2000)) -> 167924.75
A6: Create a new subsheet named "Monthly Trend" showing: - Column A: Month (extracted from Transaction Date, formatted as MMM-YYYY, e.g., Jul-2024) - Column B: Monthly Revenue (sum of Final Amount for that month, Active + INR only) - Column C: Cumulative Revenue (running total up to that month) - Column D: MoM Growth % = (Current Month − Previous Month) / Previous Month × 100. First month = "N/A". All values must be formula-driven. Write the month with the highest MoM growth % in cell B5. | B6: {=INDEX('Monthly Trend'!A2:A1000, MATCH(MAX('Monthly Trend'!D2:D1000), 'Monthly Trend'!D2:D1000, 0))} -> 2025-01
A7: How many unique customers have at least one "Active" transaction AND at least one "Cancelled" or "Churned" transaction? (A customer counts only if they appear in BOTH categories) Write the count (using formula) in cell B6. | B7: {=SUMPRODUCT((COUNTIFS(Transactions!$C$2:$C$200, UNIQUE(TRIM(Transactions!$C$2:$C$200)), Transactions!$P$2:$P$200, "Active")>0) * (COUNTIFS(Transactions!$C$2:$C$200, UNIQUE(TRIM(Transactions!$C$2:$C$200)), Transactions!$P$2:$P$200, "Cancelled") + COUNTIFS(Transactions!$C$2:$C$200, UNIQUE(TRIM(Transactions!$C$2:$C$200)), Transactions!$P$2:$P$200, "Churned")>0))} -> 27

Sheet Region Summary
E2: {=IF(B2:B1000="",, B2:B1000 / C2:C1000)} -> 6155.0077
E3: 15000.566
E4: 4207.412
E5: 7227.9782
E6: 8263.7299

Sheet Monthly Trend
A1: Month | B1: Monthly Revenue | C1: Cumulative Revenue | D1: MoM Growth %
A2: 2024-07 | B2: =SUMPRODUCT( (IFERROR(TEXT(Transactions!$B$2:$B$2000, "yyyy-mm"), RIGHT(Transactions!$B$2:$B$2000, 4)&"-"&MID(Transactions!$B$2:$B$2000, 4, 2)) = A2) * (Transactions!$P$2:$P$2000 = "Active") * (Transactions!$M$2:$M$2000 = "INR") * Transactions!$T$2:$T$2000 ) -> 64215.244 | C2: =B2 -> 64215.244 | D2: N/A
A3: 2024-08 | B3: =SUMPRODUCT( (IFERROR(TEXT(Transactions!$B$2:$B$2000, "yyyy-mm"), RIGHT(Transactions!$B$2:$B$2000, 4)&"-"&MID(Transactions!$B$2:$B$2000, 4, 2)) = A3) * (Transactions!$P$2:$P$2000 = "Active") * (Transactions!$M$2:$M$2000 = "INR") * Transactions!$T$2:$T$2000 ) -> 104148.37 | C3: =C2 + B3 -> 168363.62 | D3: =(B3-B2)/B2 -> 0.6218637
A4: 27-08-2024 | B4: =SUMPRODUCT( (IFERROR(TEXT(Transactions!$B$2:$B$2000, "yyyy-mm"), RIGHT(Transactions!$B$2:$B$2000, 4)&"-"&MID(Transactions!$B$2:$B$2000, 4, 2)) = A4) * (Transactions!$P$2:$P$2000 = "Active") * (Transactions!$M$2:$M$2000 = "INR") * Transactions!$T$2:$T$2000 ) -> 0 | C4: =C3 + B4 -> 168363.62 | D4: N/A
A5: 2024-09 | B5: =SUMPRODUCT( (IFERROR(TEXT(Transactions!$B$2:$B$2000, "yyyy-mm"), RIGHT(Transactions!$B$2:$B$2000, 4)&"-"&MID(Transactions!$B$2:$B$2000, 4, 2)) = A5) * (Transactions!$P$2:$P$2000 = "Active") * (Transactions!$M$2:$M$2000 = "INR") * Transactions!$T$2:$T$2000 ) -> 72642.698 | C5: =C4 + B5 -> 241006.32 | D5: =(B5-B3)/B3 -> -0.30250761
A6: 2024-10 | B6: =SUMPRODUCT( (IFERROR(TEXT(Transactions!$B$2:$B$2000, "yyyy-mm"), RIGHT(Transactions!$B$2:$B$2000, 4)&"-"&MID(Transactions!$B$2:$B$2000, 4, 2)) = A6) * (Transactions!$P$2:$P$2000 = "Active") * (Transactions!$M$2:$M$2000 = "INR") * Transactions!$T$2:$T$2000 ) -> 22074.427 | C6: =C5 + B6 -> 263080.74 | D6: =(B6-B5)/B5 -> -0.69612325
A7: 2024-11 | B7: =SUMPRODUCT( (IFERROR(TEXT(Transactions!$B$2:$B$2000, "yyyy-mm"), RIGHT(Transactions!$B$2:$B$2000, 4)&"-"&MID(Transactions!$B$2:$B$2000, 4, 2)) = A7) * (Transactions!$P$2:$P$2000 = "Active") * (Transactions!$M$2:$M$2000 = "INR") * Transactions!$T$2:$T$2000 ) -> 196104.06 | C7: =C6 + B7 -> 459184.8 | D7: =(B7-B6)/B6 -> 7.8837666
A8: 2024-12 | B8: =SUMPRODUCT( (IFERROR(TEXT(Transactions!$B$2:$B$2000, "yyyy-mm"), RIGHT(Transactions!$B$2:$B$2000, 4)&"-"&MID(Transactions!$B$2:$B$2000, 4, 2)) = A8) * (Transactions!$P$2:$P$2000 = "Active") * (Transactions!$M$2:$M$2000 = "INR") * Transactions!$T$2:$T$2000 ) -> 9593.2515 | C8: =C7 + B8 -> 468778.05 | D8: =(B8-B7)/B7 -> -0.95108081
A9: 2025-01 | B9: =SUMPRODUCT( (IFERROR(TEXT(Transactions!$B$2:$B$2000, "yyyy-mm"), RIGHT(Transactions!$B$2:$B$2000, 4)&"-"&MID(Transactions!$B$2:$B$2000, 4, 2)) = A9) * (Transactions!$P$2:$P$2000 = "Active") * (Transactions!$M$2:$M$2000 = "INR") * Transactions!$T$2:$T$2000 ) -> 87251.879 | C9: =C8 + B9 -> 556029.93 | D9: =(B9-B8)/B8 -> 8.0951309
A10: 2025-02 | B10: =SUMPRODUCT( (IFERROR(TEXT(Transactions!$B$2:$B$2000, "yyyy-mm"), RIGHT(Transactions!$B$2:$B$2000, 4)&"-"&MID(Transactions!$B$2:$B$2000, 4, 2)) = A10) * (Transactions!$P$2:$P$2000 = "Active") * (Transactions!$M$2:$M$2000 = "INR") * Transactions!$T$2:$T$2000 ) -> 11002.547 | C10: =C9 + B10 -> 567032.48 | D10: =(B10-B9)/B9 -> -0.87389902
A11: 20-02-2025 | B11: =SUMPRODUCT( (IFERROR(TEXT(Transactions!$B$2:$B$2000, "yyyy-mm"), RIGHT(Transactions!$B$2:$B$2000, 4)&"-"&MID(Transactions!$B$2:$B$2000, 4, 2)) = A11) * (Transactions!$P$2:$P$2000 = "Active") * (Transactions!$M$2:$M$2000 = "INR") * Transactions!$T$2:$T$2000 ) -> 0 | C11: =C10 + B11 -> 567032.48 | D11: N/A
A12: 2025-03 | B12: =SUMPRODUCT( (IFERROR(TEXT(Transactions!$B$2:$B$2000, "yyyy-mm"), RIGHT(Transactions!$B$2:$B$2000, 4)&"-"&MID(Transactions!$B$2:$B$2000, 4, 2)) = A12) * (Transactions!$P$2:$P$2000 = "Active") * (Transactions!$M$2:$M$2000 = "INR") * Transactions!$T$2:$T$2000 ) -> 79148.064 | C12: =C11 + B12 -> 646180.54 | D12: =(B12-B10)/B10 -> 6.1936129
A13: 31-03-2025 | B13: =SUMPRODUCT( (IFERROR(TEXT(Transactions!$B$2:$B$2000, "yyyy-mm"), RIGHT(Transactions!$B$2:$B$2000, 4)&"-"&MID(Transactions!$B$2:$B$2000, 4, 2)) = A13) * (Transactions!$P$2:$P$2000 = "Active") * (Transactions!$M$2:$M$2000 = "INR") * Transactions!$T$2:$T$2000 ) -> 11797.64 | C13: =C12 + B13 -> 657978.18 | D13: N/A
A14: 2025-04 | B14: =SUMPRODUCT( (IFERROR(TEXT(Transactions!$B$2:$B$2000, "yyyy-mm"), RIGHT(Transactions!$B$2:$B$2000, 4)&"-"&MID(Transactions!$B$2:$B$2000, 4, 2)) = A14) * (Transactions!$P$2:$P$2000 = "Active") * (Transactions!$M$2:$M$2000 = "INR") * Transactions!$T$2:$T$2000 ) -> 52654.162 | C14: =C13 + B14 -> 710632.34 | D14: =(B14-(B13+B12))/(B13+B12) -> -0.42103739
A15: 2025-05 | B15: =SUMPRODUCT( (IFERROR(TEXT(Transactions!$B$2:$B$2000, "yyyy-mm"), RIGHT(Transactions!$B$2:$B$2000, 4)&"-"&MID(Transactions!$B$2:$B$2000, 4, 2)) = A15) * (Transactions!$P$2:$P$2000 = "Active") * (Transactions!$M$2:$M$2000 = "INR") * Transactions!$T$2:$T$2000 ) -> 36873.134 | C15: =C14 + B15 -> 747505.48 | D15: =(B15-B14)/B14 -> -0.29971094
A16: 2025-06 | B16: =SUMPRODUCT( (IFERROR(TEXT(Transactions!$B$2:$B$2000, "yyyy-mm"), RIGHT(Transactions!$B$2:$B$2000, 4)&"-"&MID(Transactions!$B$2:$B$2000, 4, 2)) = A16) * (Transactions!$P$2:$P$2000 = "Active") * (Transactions!$M$2:$M$2000 = "INR") * Transactions!$T$2:$T$2000 ) -> 94659.603 | C16: =C15 + B16 -> 842165.08 | D16: =(B16-B15)/B15 -> 1.56717
A17: 2025-09 | B17: =SUMPRODUCT( (IFERROR(TEXT(Transactions!$B$2:$B$2000, "yyyy-mm"), RIGHT(Transactions!$B$2:$B$2000, 4)&"-"&MID(Transactions!$B$2:$B$2000, 4, 2)) = A17) * (Transactions!$P$2:$P$2000 = "Active") * (Transactions!$M$2:$M$2000 = "INR") * Transactions!$T$2:$T$2000 ) -> 8999.1 | C17: =C16 + B17 -> 851164.18 | D17: =(B17-B16)/B16 -> -0.90493199
